Octopus/__init__.py
Octopus/OctopusCore/WebEventListener.py
Octopus/OctopusCore/__init__.py
Octopus/OctopusCore/browsing.py
Octopus/OctopusCore/common.py
Octopus/OctopusCore/configuration.py
Octopus/OctopusCore/dataManager.py
Octopus/OctopusCore/driver.py
Octopus/OctopusCore/executer.py
Octopus/OctopusCore/globals.py
Octopus/OctopusCore/reporter.py
Octopus/OctopusCore/selenium_extensions.py
Octopus/OctopusHTMLReport/OctopusHTMLTestReport.py
Octopus/OctopusHTMLReport/OctopusHTMLTestReportGrouped.py
Octopus/OctopusHTMLReport/OctopusReporter.py
Octopus/OctopusHTMLReport/OctopusTestCase.py
Octopus/OctopusHTMLReport/OctopusTestResult.py
Octopus/OctopusHTMLReport/__init__.py
the_octopus_test-2.0.12.dist-info/LICENSE
the_octopus_test-2.0.12.dist-info/METADATA
the_octopus_test-2.0.12.dist-info/WHEEL
the_octopus_test-2.0.12.dist-info/top_level.txt
the_octopus_test-2.0.12.dist-info/RECORD
