Metadata-Version: 2.1
Name: the-octopus-test
Version: 2.0.12
Summary: The-Octopus-Test is a Python project for E2E testing, based on Selenium, Appium and the Test Automation Hybrid Framework concepts.
Home-page: https://the-octopus.github.io/
Author: Abdelghany Abdelaziz
Author-email: abdelghany_elaziz@hotmail.com
Project-URL: Documentation, https://the-octopus.github.io/
Project-URL: Source, https://github.com/the-octopus/octopus-sample-test/
Project-URL: Tracker, https://github.com/the-octopus/octopus-sample-test/issues
Keywords: test,automation,framework,hybrid,octopus,the-octopus,the-octopus-test,selenium,appium,keyword driven,data driven
Classifier: Development Status :: 3 - Alpha
Classifier: Intended Audience :: Developers
Classifier: Topic :: Software Development :: Build Tools
Classifier: License :: OSI Approved :: MIT License
Classifier: Programming Language :: Python :: 3
Classifier: Programming Language :: Python :: 3.5
Classifier: Programming Language :: Python :: 3.6
Classifier: Programming Language :: Python :: 3.7
Classifier: Programming Language :: Python :: 3.8
Classifier: Programming Language :: Python :: 3 :: Only
Requires-Python: >=3.5, <4
License-File: LICENSE
Requires-Dist: selenium
Requires-Dist: Appium-Python-Client
Requires-Dist: pyodbc
Requires-Dist: requests
Requires-Dist: Flask
Requires-Dist: PyJWT
